fpga4p/__init__.py
fpga4p/core.py
fpga4p/launch.py
fpga4p/classification_algorithms/__init__.py
fpga4p/classification_algorithms/nbc_c.py
fpga4p/supporting_tools/__init__.py
fpga4p/supporting_tools/notifications.py
fpga4p/supporting_tools/special_characters.py
fpga4p/supporting_tools/supporting_functions.py
fpga4p/testing/__init__.py
fpga4p/testing/accuracy_testing.py
fpga4p/training_algorithms/__init__.py
fpga4p/training_algorithms/nbc_t.py
fpga4p/training_algorithms/nbc_verilog.sv
fpga4p-2.1.dist-info/DESCRIPTION.rst
fpga4p-2.1.dist-info/METADATA
fpga4p-2.1.dist-info/RECORD
fpga4p-2.1.dist-info/WHEEL
fpga4p-2.1.dist-info/entry_points.txt
fpga4p-2.1.dist-info/metadata.json
fpga4p-2.1.dist-info/top_level.txt
