Metadata-Version: 2.0
Name: fpga4p
Version: 2.1
Summary: Python package / GNU Linux terminal utility for porting machine learning algorithms to FPGA.
Home-page: UNKNOWN
Author: Dmitriy Mandjiev, Pavel Ivanov
Author-email: fmnpro19@gmail.com
License: UNKNOWN
Platform: UNKNOWN
Requires-Dist: Click
Requires-Dist: singleton-decorator
Requires-Dist: pyserial
Requires-Dist: colorama
Requires-Dist: pandas
Requires-Dist: setuptools
